PyCpp/__init__.py
PyCpp/iostream.py
Py.Cpp-0.1.post1.dist-info/LICENSE
Py.Cpp-0.1.post1.dist-info/METADATA
Py.Cpp-0.1.post1.dist-info/WHEEL
Py.Cpp-0.1.post1.dist-info/top_level.txt
Py.Cpp-0.1.post1.dist-info/RECORD
