Metadata-Version: 2.1
Name: Py.Cpp
Version: 0.1.post1
Summary: An effort to bring Cpp like syntax to Python
Home-page: https://github.com/WizzyGeek/PyCpp
License: MIT License
Project-URL: Source, https://github.com/WizzyGeek/PyCpp
Project-URL: Tracker, https://github.com/WizzyGeek/PyCpp/issues
Project-URL: Download, https://pypi.org/project/Py.Cpp/#files
Keywords: c++,cpp,cpp.py,PyCpp,pycpp
Platform: UNKNOWN
Classifier: License :: OSI Approved :: MIT License
Classifier: Programming Language :: Python :: 3.8
Classifier: Programming Language :: Python :: 3.9
Requires-Dist: forbiddenfruit
